[ {
  "firstName" : "Johnathon",
  "lastName" : "Sanjuan",
  "employeeId" : 1,
  "email" : "Johnathon_Sanjuan@crystalsecurity.com",
  "companyId" : 1,
  "companyName" : "Crystal Security",
  "positionTitle" : "CEO",
  "startDate" : "2016-05-04"
}, {
  "firstName" : "Synthia",
  "lastName" : "Howse",
  "employeeId" : 2,
  "email" : "Synthia_Howse@crystalsecurity.com",
  "companyId" : 1,
  "companyName" : "Crystal Security",
  "managerId" : 1,
  "positionTitle" : "Engineering Manager",
  "startDate" : "2010-12-12"
}, {
  "firstName" : "Teresita",
  "lastName" : "Eyer",
  "employeeId" : 3,
  "email" : "Teresita_Eyer@crystalsecurity.com",
  "companyId" : 1,
  "companyName" : "Crystal Security",
  "managerId" : 1,
  "positionTitle" : "Engineering Manager",
  "startDate" : "2011-12-23"
}, {
  "firstName" : "Spring",
  "lastName" : "Squier",
  "employeeId" : 4,
  "email" : "Spring_Squier@crystalsecurity.com",
  "companyId" : 1,
  "companyName" : "Crystal Security",
  "managerId" : 1,
  "positionTitle" : "Engineering Manager",
  "startDate" : "1999-08-06"
}, {
  "firstName" : "Windy",
  "lastName" : "Maske",
  "employeeId" : 5,
  "email" : "Windy_Maske@crystalsecurity.com",
  "companyId" : 1,
  "companyName" : "Crystal Security",
  "managerId" : 4,
  "positionTitle" : "Engineering Manager",
  "startDate" : "2015-12-01"
}, {
  "firstName" : "Roland",
  "lastName" : "Hickmon",
  "employeeId" : 6,
  "email" : "Roland_Hickmon@crystalsecurity.com",
  "companyId" : 1,
  "companyName" : "Crystal Security",
  "managerId" : 2,
  "positionTitle" : "Engineering Manager",
  "startDate" : "1992-03-31"
}, {
  "firstName" : "Bunny",
  "lastName" : "Sonnier",
  "employeeId" : 7,
  "email" : "Bunny_Sonnier@crystalsecurity.com",
  "companyId" : 1,
  "companyName" : "Crystal Security",
  "managerId" : 2,
  "positionTitle" : "Engineering Manager",
  "startDate" : "1992-05-20"
}, {
  "firstName" : "Arron",
  "lastName" : "Brazeal",
  "employeeId" : 8,
  "email" : "Arron_Brazeal@crystalsecurity.com",
  "companyId" : 1,
  "companyName" : "Crystal Security",
  "managerId" : 4,
  "positionTitle" : "Engineering Manager",
  "startDate" : "2014-12-18"
}, {
  "firstName" : "Song",
  "lastName" : "Bulow",
  "employeeId" : 9,
  "email" : "Song_Bulow@crystalsecurity.com",
  "companyId" : 1,
  "companyName" : "Crystal Security",
  "managerId" : 7,
  "positionTitle" : "Engineering Manager",
  "startDate" : "1998-03-03"
}, {
  "firstName" : "Suzan",
  "lastName" : "Hinch",
  "employeeId" : 10,
  "email" : "Suzan_Hinch@crystalsecurity.com",
  "companyId" : 1,
  "companyName" : "Crystal Security",
  "managerId" : 5,
  "positionTitle" : "Tech Lead",
  "startDate" : "1992-05-29"
}, {
  "firstName" : "Jeanie",
  "lastName" : "Fines",
  "employeeId" : 11,
  "email" : "Jeanie_Fines@crystalsecurity.com",
  "companyId" : 1,
  "companyName" : "Crystal Security",
  "managerId" : 4,
  "positionTitle" : "Software Engineer II",
  "startDate" : "1997-02-04"
}, {
  "firstName" : "Kalyn",
  "lastName" : "Bosarge",
  "employeeId" : 12,
  "email" : "Kalyn_Bosarge@crystalsecurity.com",
  "companyId" : 1,
  "companyName" : "Crystal Security",
  "managerId" : 3,
  "positionTitle" : "Tech Lead",
  "startDate" : "1991-01-22"
}, {
  "firstName" : "Eusebia",
  "lastName" : "Voss",
  "employeeId" : 13,
  "email" : "Eusebia_Voss@crystalsecurity.com",
  "companyId" : 1,
  "companyName" : "Crystal Security",
  "managerId" : 3,
  "positionTitle" : "Senior Software Engineer",
  "startDate" : "1990-07-24"
}, {
  "firstName" : "Aletha",
  "lastName" : "Lipari",
  "employeeId" : 14,
  "email" : "Aletha_Lipari@crystalsecurity.com",
  "companyId" : 1,
  "companyName" : "Crystal Security",
  "managerId" : 5,
  "positionTitle" : "Software Engineer I",
  "startDate" : "1999-08-07"
}, {
  "firstName" : "Linnie",
  "lastName" : "Cho",
  "employeeId" : 15,
  "email" : "Linnie_Cho@crystalsecurity.com",
  "companyId" : 1,
  "companyName" : "Crystal Security",
  "managerId" : 2,
  "positionTitle" : "Software Engineer II",
  "startDate" : "2004-12-09"
}, {
  "firstName" : "Ardis",
  "lastName" : "Espino",
  "employeeId" : 16,
  "email" : "Ardis_Espino@crystalsecurity.com",
  "companyId" : 1,
  "companyName" : "Crystal Security",
  "managerId" : 4,
  "positionTitle" : "Software Architect",
  "startDate" : "2000-07-19"
}, {
  "firstName" : "Ariana",
  "lastName" : "Strom",
  "employeeId" : 17,
  "email" : "Ariana_Strom@crystalsecurity.com",
  "companyId" : 1,
  "companyName" : "Crystal Security",
  "managerId" : 8,
  "positionTitle" : "Software Engineer II",
  "startDate" : "2002-07-08"
}, {
  "firstName" : "Fredia",
  "lastName" : "Vogelsang",
  "employeeId" : 18,
  "email" : "Fredia_Vogelsang@crystalsecurity.com",
  "companyId" : 1,
  "companyName" : "Crystal Security",
  "managerId" : 7,
  "positionTitle" : "Senior Software Engineer",
  "startDate" : "2016-05-01"
}, {
  "firstName" : "Shante",
  "lastName" : "Woodford",
  "employeeId" : 19,
  "email" : "Shante_Woodford@crystalsecurity.com",
  "companyId" : 1,
  "companyName" : "Crystal Security",
  "managerId" : 6,
  "positionTitle" : "Tech Lead",
  "startDate" : "1994-02-02"
}, {
  "firstName" : "Mireille",
  "lastName" : "Mahn",
  "employeeId" : 20,
  "email" : "Mireille_Mahn@crystalsecurity.com",
  "companyId" : 1,
  "companyName" : "Crystal Security",
  "managerId" : 7,
  "positionTitle" : "Software Engineer I",
  "startDate" : "1998-06-13"
}, {
  "firstName" : "Elana",
  "lastName" : "Troutt",
  "employeeId" : 21,
  "email" : "Elana_Troutt@crystalsecurity.com",
  "companyId" : 1,
  "companyName" : "Crystal Security",
  "managerId" : 6,
  "positionTitle" : "Software Engineer II",
  "startDate" : "1990-06-19"
}, {
  "firstName" : "Ami",
  "lastName" : "Keithley",
  "employeeId" : 22,
  "email" : "Ami_Keithley@crystalsecurity.com",
  "companyId" : 1,
  "companyName" : "Crystal Security",
  "managerId" : 4,
  "positionTitle" : "Software Architect",
  "startDate" : "2016-03-04"
}, {
  "firstName" : "Kristian",
  "lastName" : "Jardine",
  "employeeId" : 23,
  "email" : "Kristian_Jardine@crystalsecurity.com",
  "companyId" : 1,
  "companyName" : "Crystal Security",
  "managerId" : 6,
  "positionTitle" : "Senior Software Engineer",
  "startDate" : "2016-02-22"
}, {
  "firstName" : "Maxine",
  "lastName" : "Town",
  "employeeId" : 24,
  "email" : "Maxine_Town@crystalsecurity.com",
  "companyId" : 1,
  "companyName" : "Crystal Security",
  "managerId" : 6,
  "positionTitle" : "Tech Lead",
  "startDate" : "2007-06-08"
}, {
  "firstName" : "Lashaun",
  "lastName" : "Setser",
  "employeeId" : 25,
  "email" : "Lashaun_Setser@crystalsecurity.com",
  "companyId" : 1,
  "companyName" : "Crystal Security",
  "managerId" : 7,
  "positionTitle" : "Software Engineer I",
  "startDate" : "2014-02-10"
}, {
  "firstName" : "Gayle",
  "lastName" : "Vantassel",
  "employeeId" : 26,
  "email" : "Gayle_Vantassel@crystalsecurity.com",
  "companyId" : 1,
  "companyName" : "Crystal Security",
  "managerId" : 5,
  "positionTitle" : "Software Architect",
  "startDate" : "2000-03-30"
}, {
  "firstName" : "Earlie",
  "lastName" : "Sessoms",
  "employeeId" : 27,
  "email" : "Earlie_Sessoms@crystalsecurity.com",
  "companyId" : 1,
  "companyName" : "Crystal Security",
  "managerId" : 4,
  "positionTitle" : "Software Architect",
  "startDate" : "2008-10-28"
}, {
  "firstName" : "Ellamae",
  "lastName" : "Harps",
  "employeeId" : 28,
  "email" : "Ellamae_Harps@crystalsecurity.com",
  "companyId" : 1,
  "companyName" : "Crystal Security",
  "managerId" : 2,
  "positionTitle" : "Software Engineer I",
  "startDate" : "2003-09-06"
}, {
  "firstName" : "Callie",
  "lastName" : "Sandrock",
  "employeeId" : 29,
  "email" : "Callie_Sandrock@crystalsecurity.com",
  "companyId" : 1,
  "companyName" : "Crystal Security",
  "managerId" : 6,
  "positionTitle" : "Senior Software Engineer",
  "startDate" : "1993-01-09"
}, {
  "firstName" : "Mae",
  "lastName" : "Brownlee",
  "employeeId" : 30,
  "email" : "Mae_Brownlee@crystalsecurity.com",
  "companyId" : 1,
  "companyName" : "Crystal Security",
  "managerId" : 7,
  "positionTitle" : "Software Architect",
  "startDate" : "2008-11-09"
}, {
  "firstName" : "Jarvis",
  "lastName" : "Dutil",
  "employeeId" : 31,
  "email" : "Jarvis_Dutil@crystalsecurity.com",
  "companyId" : 1,
  "companyName" : "Crystal Security",
  "managerId" : 7,
  "positionTitle" : "Software Architect",
  "startDate" : "1990-07-20"
}, {
  "firstName" : "Evelin",
  "lastName" : "Gaddy",
  "employeeId" : 32,
  "email" : "Evelin_Gaddy@crystalsecurity.com",
  "companyId" : 1,
  "companyName" : "Crystal Security",
  "managerId" : 7,
  "positionTitle" : "Senior Software Engineer",
  "startDate" : "1998-09-27"
}, {
  "firstName" : "Dimple",
  "lastName" : "Lynam",
  "employeeId" : 33,
  "email" : "Dimple_Lynam@crystalsecurity.com",
  "companyId" : 1,
  "companyName" : "Crystal Security",
  "managerId" : 3,
  "positionTitle" : "Senior Software Engineer",
  "startDate" : "2010-07-04"
}, {
  "firstName" : "Leo",
  "lastName" : "Bretz",
  "employeeId" : 34,
  "email" : "Leo_Bretz@crystalsecurity.com",
  "companyId" : 1,
  "companyName" : "Crystal Security",
  "managerId" : 6,
  "positionTitle" : "Software Engineer I",
  "startDate" : "2015-08-02"
}, {
  "firstName" : "Lavette",
  "lastName" : "Wunsch",
  "employeeId" : 35,
  "email" : "Lavette_Wunsch@crystalsecurity.com",
  "companyId" : 1,
  "companyName" : "Crystal Security",
  "managerId" : 2,
  "positionTitle" : "Software Engineer I",
  "startDate" : "2008-03-04"
}, {
  "firstName" : "Maryellen",
  "lastName" : "Niblett",
  "employeeId" : 36,
  "email" : "Maryellen_Niblett@crystalsecurity.com",
  "companyId" : 1,
  "companyName" : "Crystal Security",
  "managerId" : 6,
  "positionTitle" : "Software Engineer II",
  "startDate" : "2015-08-26"
}, {
  "firstName" : "Florinda",
  "lastName" : "Quist",
  "employeeId" : 37,
  "email" : "Florinda_Quist@crystalsecurity.com",
  "companyId" : 1,
  "companyName" : "Crystal Security",
  "managerId" : 5,
  "positionTitle" : "Senior Software Engineer",
  "startDate" : "2002-11-04"
}, {
  "firstName" : "Rosalva",
  "lastName" : "Lawhorn",
  "employeeId" : 38,
  "email" : "Rosalva_Lawhorn@crystalsecurity.com",
  "companyId" : 1,
  "companyName" : "Crystal Security",
  "managerId" : 6,
  "positionTitle" : "Senior Software Engineer",
  "startDate" : "2001-01-24"
}, {
  "firstName" : "Shanika",
  "lastName" : "Scher",
  "employeeId" : 39,
  "email" : "Shanika_Scher@crystalsecurity.com",
  "companyId" : 1,
  "companyName" : "Crystal Security",
  "managerId" : 4,
  "positionTitle" : "Software Architect",
  "startDate" : "1999-07-30"
}, {
  "firstName" : "Lovella",
  "lastName" : "Burgett",
  "employeeId" : 40,
  "email" : "Lovella_Burgett@crystalsecurity.com",
  "companyId" : 1,
  "companyName" : "Crystal Security",
  "managerId" : 8,
  "positionTitle" : "Tech Lead",
  "startDate" : "2003-02-14"
}, {
  "firstName" : "Roseanne",
  "lastName" : "Peralta",
  "employeeId" : 41,
  "email" : "Roseanne_Peralta@crystalsecurity.com",
  "companyId" : 1,
  "companyName" : "Crystal Security",
  "managerId" : 8,
  "positionTitle" : "Senior Software Engineer",
  "startDate" : "2012-11-13"
}, {
  "firstName" : "Stefani",
  "lastName" : "Charlesworth",
  "employeeId" : 42,
  "email" : "Stefani_Charlesworth@crystalsecurity.com",
  "companyId" : 1,
  "companyName" : "Crystal Security",
  "managerId" : 8,
  "positionTitle" : "Tech Lead",
  "startDate" : "2015-11-23"
}, {
  "firstName" : "Shanell",
  "lastName" : "Mahi",
  "employeeId" : 43,
  "email" : "Shanell_Mahi@crystalsecurity.com",
  "companyId" : 1,
  "companyName" : "Crystal Security",
  "managerId" : 9,
  "positionTitle" : "Software Engineer I",
  "startDate" : "1992-07-29"
}, {
  "firstName" : "Camie",
  "lastName" : "Gunnels",
  "employeeId" : 44,
  "email" : "Camie_Gunnels@crystalsecurity.com",
  "companyId" : 1,
  "companyName" : "Crystal Security",
  "managerId" : 6,
  "positionTitle" : "Software Architect",
  "startDate" : "2004-05-22"
}, {
  "firstName" : "Lilly",
  "lastName" : "Magrath",
  "employeeId" : 45,
  "email" : "Lilly_Magrath@crystalsecurity.com",
  "companyId" : 1,
  "companyName" : "Crystal Security",
  "managerId" : 4,
  "positionTitle" : "Senior Software Engineer",
  "startDate" : "1993-11-15"
}, {
  "firstName" : "Sharice",
  "lastName" : "Punch",
  "employeeId" : 46,
  "email" : "Sharice_Punch@crystalsecurity.com",
  "companyId" : 1,
  "companyName" : "Crystal Security",
  "managerId" : 5,
  "positionTitle" : "Tech Lead",
  "startDate" : "2010-01-10"
}, {
  "firstName" : "Louise",
  "lastName" : "Montes",
  "employeeId" : 47,
  "email" : "Louise_Montes@crystalsecurity.com",
  "companyId" : 1,
  "companyName" : "Crystal Security",
  "managerId" : 2,
  "positionTitle" : "Senior Software Engineer",
  "startDate" : "2014-02-15"
}, {
  "firstName" : "Ilene",
  "lastName" : "Ralston",
  "employeeId" : 48,
  "email" : "Ilene_Ralston@crystalsecurity.com",
  "companyId" : 1,
  "companyName" : "Crystal Security",
  "managerId" : 8,
  "positionTitle" : "Software Engineer II",
  "startDate" : "1996-11-23"
}, {
  "firstName" : "Mistie",
  "lastName" : "Bethel",
  "employeeId" : 49,
  "email" : "Mistie_Bethel@crystalsecurity.com",
  "companyId" : 1,
  "companyName" : "Crystal Security",
  "managerId" : 6,
  "positionTitle" : "Software Engineer I",
  "startDate" : "2011-12-22"
}, {
  "firstName" : "Shelba",
  "lastName" : "Macinnis",
  "employeeId" : 50,
  "email" : "Shelba_Macinnis@crystalsecurity.com",
  "companyId" : 1,
  "companyName" : "Crystal Security",
  "managerId" : 6,
  "positionTitle" : "Software Architect",
  "startDate" : "1995-02-19"
} ]